bsm_api_client/__init__.py
bsm_api_client/api_client.py
bsm_api_client/client_base.py
bsm_api_client/exceptions.py
bsm_api_client/models.py
bsm_api_client/websocket_client.py
bsm_api_client/cli/__init__.py
bsm_api_client/cli/__main__.py
bsm_api_client/cli/account.py
bsm_api_client/cli/addon.py
bsm_api_client/cli/allowlist.py
bsm_api_client/cli/auth.py
bsm_api_client/cli/backup.py
bsm_api_client/cli/config.py
bsm_api_client/cli/content.py
bsm_api_client/cli/decorators.py
bsm_api_client/cli/main_menus.py
bsm_api_client/cli/permissions.py
bsm_api_client/cli/player.py
bsm_api_client/cli/plugins.py
bsm_api_client/cli/properties.py
bsm_api_client/cli/server.py
bsm_api_client/cli/system.py
bsm_api_client/cli/world.py
bsm_api_client/client/__init__.py
bsm_api_client/client/_account_methods.py
bsm_api_client/client/_content_methods.py
bsm_api_client/client/_manager_methods.py
bsm_api_client/client/_plugin_methods.py
bsm_api_client/client/_server_action_methods.py
bsm_api_client/client/_server_info_methods.py
bsm_api_client-1.4.0.dist-info/licenses/LICENSE
bsm_api_client-1.4.0.dist-info/METADATA
bsm_api_client-1.4.0.dist-info/WHEEL
bsm_api_client-1.4.0.dist-info/entry_points.txt
bsm_api_client-1.4.0.dist-info/top_level.txt
bsm_api_client-1.4.0.dist-info/RECORD
