Metadata-Version: 2.4
Name: bsm-api-client
Version: 1.4.0
Summary: A Python client library for the Bedrock Server Manager API
Author-email: DMedina559 <dmedina559-github@outlook.com>
Project-URL: Homepage, https://github.com/DMedina559/bsm-api-client
Project-URL: Bug Tracker, https://github.com/DMedina559/bsm-api-client/issues
Project-URL: Changelog, https://github.com/DMedina559/bsm-api-client/blob/main/docs/CHANGELOG.md
Keywords: minecraft,bedrock,server,manager,api,client,asyncio,aiohttp,bsm
Classifier: Programming Language :: Python :: 3
Classifier: Programming Language :: Python :: 3.11
Classifier: Programming Language :: Python :: 3.12
Classifier: Programming Language :: Python :: 3.13
Classifier: Operating System :: OS Independent
Classifier: Intended Audience :: Developers
Classifier: Topic :: Software Development :: Libraries :: Python Modules
Classifier: Framework :: AsyncIO
Requires-Python: >=3.11
License-File: LICENSE
Requires-Dist: aiohttp<4.0.0,>=3.8.0
Requires-Dist: pydantic<2.13,>=2.11.0
Provides-Extra: dev
Requires-Dist: pytest<9.1,>=8.4.0; extra == "dev"
Requires-Dist: pytest-mock<3.16,>=3.14.0; extra == "dev"
Requires-Dist: pytest-asyncio<1.4,>=1.1.0; extra == "dev"
Requires-Dist: black<25.12,>=25.1.0; extra == "dev"
Requires-Dist: flake8<7.4,>=7.3.0; extra == "dev"
Requires-Dist: isort<7.1,>=5.13.0; extra == "dev"
Requires-Dist: mypy<1.20,>=1.10.0; extra == "dev"
Requires-Dist: bedrock-server-manager<3.8.0,>=3.7.1; extra == "dev"
Provides-Extra: cli
Requires-Dist: click<8.4,>=8.2.0; extra == "cli"
Requires-Dist: questionary<2.2,>=2.1.0; extra == "cli"
Dynamic: license-file
